drf_protector/__init__.py
drf_protector/cli.py
drf_protector/dockerizer.py
drf_protector/obfuscator.py
drf_protector/utils.py
drf_protector/__pycache__/__init__.cpython-313.pyc
drf_protector/__pycache__/cli.cpython-313.pyc
drf_protector/__pycache__/dockerizer.cpython-313.pyc
drf_protector/__pycache__/obfuscator.cpython-313.pyc
drf_protector/__pycache__/utils.cpython-313.pyc
drf_protector-0.1.1.dist-info/METADATA
drf_protector-0.1.1.dist-info/WHEEL
drf_protector-0.1.1.dist-info/entry_points.txt
drf_protector-0.1.1.dist-info/top_level.txt
drf_protector-0.1.1.dist-info/RECORD
